LICENSE
MANIFEST.in
README.rst
VERSION
setup.cfg
setup.py
src/stepfunctions/__init__.py
src/stepfunctions/exceptions.py
src/stepfunctions.egg-info/PKG-INFO
src/stepfunctions.egg-info/SOURCES.txt
src/stepfunctions.egg-info/dependency_links.txt
src/stepfunctions.egg-info/requires.txt
src/stepfunctions.egg-info/top_level.txt
src/stepfunctions/inputs/__init__.py
src/stepfunctions/inputs/placeholders.py
src/stepfunctions/inputs/utils.py
src/stepfunctions/steps/__init__.py
src/stepfunctions/steps/choice_rule.py
src/stepfunctions/steps/compute.py
src/stepfunctions/steps/fields.py
src/stepfunctions/steps/integration_resources.py
src/stepfunctions/steps/sagemaker.py
src/stepfunctions/steps/service.py
src/stepfunctions/steps/states.py
src/stepfunctions/steps/utils.py
src/stepfunctions/template/__init__.py
src/stepfunctions/template/utils.py
src/stepfunctions/template/pipeline/__init__.py
src/stepfunctions/template/pipeline/common.py
src/stepfunctions/template/pipeline/inference.py
src/stepfunctions/template/pipeline/train.py
src/stepfunctions/workflow/__init__.py
src/stepfunctions/workflow/cloudformation.py
src/stepfunctions/workflow/stepfunctions.py
src/stepfunctions/workflow/utils.py
src/stepfunctions/workflow/widgets/__init__.py
src/stepfunctions/workflow/widgets/events_table.py
src/stepfunctions/workflow/widgets/executions_table.py
src/stepfunctions/workflow/widgets/graph.py
src/stepfunctions/workflow/widgets/utils.py
src/stepfunctions/workflow/widgets/workflows_table.py