Metadata-Version: 2.1
Name: stepfunctions
Version: 2.3.0
Summary: Open source library for developing data science workflows on AWS Step Functions.
Home-page: https://github.com/aws/aws-step-functions-data-science-sdk-python
Author: Amazon Web Services
License: Apache License 2.0
Keywords: ML Amazon AWS AI Tensorflow MXNet
Platform: UNKNOWN
Classifier: Intended Audience :: Developers
Classifier: Natural Language :: English
Classifier: License :: OSI Approved :: Apache Software License
Classifier: Programming Language :: Python
Classifier: Programming Language :: Python :: 3.6
Provides-Extra: test
